MANIFEST.in
README.rst
setup.cfg
setup.py
c2/__init__.py
c2.splitter.janome.egg-info/PKG-INFO
c2.splitter.janome.egg-info/SOURCES.txt
c2.splitter.janome.egg-info/dependency_links.txt
c2.splitter.janome.egg-info/entry_points.txt
c2.splitter.janome.egg-info/namespace_packages.txt
c2.splitter.janome.egg-info/not-zip-safe
c2.splitter.janome.egg-info/requires.txt
c2.splitter.janome.egg-info/top_level.txt
c2/splitter/__init__.py
c2/splitter/janome/__init__.py
c2/splitter/janome/configure.zcml
c2/splitter/janome/janome.py
c2/splitter/janome/tests.py
c2/splitter/janome/version.txt
docs/LICENSE.GPL
docs/LICENSE.txt