Metadata-Version: 1.1
Name: c2.splitter.janome
Version: 0.1.0
Summary: This product is split word by janome for Plone.
Home-page: https://github.com/nakagami/c2.splitter.janome
Author: Manabu TERADA, Hajime Nakagami
Author-email: terada@cmscom.jp, nakagami@gmail.com
License: GPL
Keywords: plone splitter
Platform: UNKNOWN
Classifier: Framework :: Plone
Classifier: Programming Language :: Python
